popd/__init__.py
popd-2019.4.11.dist-info/METADATA
popd-2019.4.11.dist-info/WHEEL
popd-2019.4.11.dist-info/top_level.txt
popd-2019.4.11.dist-info/RECORD
