Metadata-Version: 2.1
Name: popd
Version: 2019.4.11
Summary: @popd decorator. restore previous current directory
Home-page: https://github.com/looking-for-a-job/popd.py
License: UNKNOWN
Keywords: popd
Platform: UNKNOWN
Classifier: Operating System :: OS Independent
Classifier: Programming Language :: Python
Classifier: Programming Language :: Python :: 2
Classifier: Programming Language :: Python :: 2.7
Classifier: Programming Language :: Python :: 3
Classifier: Programming Language :: Python :: 3.4
Classifier: Programming Language :: Python :: 3.5
Classifier: Programming Language :: Python :: 3.6
Classifier: Programming Language :: Python :: 3.7
Requires-Dist: public
Requires-Dist: setuptools
